flinks/__init__.py
flinks/baseapi.py
flinks/client.py
flinks/exceptions.py
flinks/entities/__init__.py
flinks/entities/banking_services.py
flinks-0.1.0a2.dist-info/LICENSE
flinks-0.1.0a2.dist-info/METADATA
flinks-0.1.0a2.dist-info/WHEEL
flinks-0.1.0a2.dist-info/top_level.txt
flinks-0.1.0a2.dist-info/RECORD
