Metadata-Version: 2.1
Name: flinks
Version: 0.1.0a2
Summary: A Python module for communicating with the Flinks.io API.
Home-page: https://github.com/impak-finance/flinks-python
Author: impak Finance
Author-email: tech@impakfinance.com
License: MIT
Keywords: flinks bank financial data institution
Platform: UNKNOWN
Classifier: Development Status :: 3 - Alpha
Classifier: Environment :: Web Environment
Classifier: Intended Audience :: Developers
Classifier: License :: OSI Approved :: MIT License
Classifier: Natural Language :: English
Classifier: Programming Language :: Python
Classifier: Programming Language :: Python :: 3
Classifier: Programming Language :: Python :: 3.4
Classifier: Programming Language :: Python :: 3.5
Classifier: Programming Language :: Python :: 3.6
Classifier: Programming Language :: Python :: 3.7
Requires-Dist: requests (>=2.0)
